Metadata-Version: 1.1
Name: mandelbrot
Version: 0.1
Summary: A program for generating Mandelbrot fractal images
Home-page: http://packages.python.org/mandelbrot
Author: Anand B Pillai
Author-email: abpillai@gmail.com
License: BSD
Keywords: fractal mandelbrot example chaos
Platform: UNKNOWN
Classifier: Development Status :: 4 - Beta
Classifier: Topic :: Scientific/Engineering :: Visualization
Classifier: License :: OSI Approved :: BSD License
